MANIFEST.in
setup.cfg
setup.py
hook/__init__.py
hook/default.yml
hook/model.py
hook/parser.py
hook/receiver.py
hook/rules.yml
hook.egg-info/PKG-INFO
hook.egg-info/SOURCES.txt
hook.egg-info/dependency_links.txt
hook.egg-info/requires.txt
hook.egg-info/top_level.txt