Metadata-Version: 1.1
Name: hook
Version: 0.0.2
Summary: A config based hook framework for github and others
Home-page: https://github.com/ssherar/hook
Author: Sam Sherar
Author-email: sbsherar@gmail.com
License: MIT license
Platform: UNKNOWN
Classifier: Development Status :: 3 - Alpha
Classifier: License :: OSI Approved :: MIT License
Classifier: Programming Language :: Python
Classifier: Programming Language :: Python :: 3
Classifier: Programming Language :: Python :: 3.3
Classifier: Programming Language :: Python :: 3.4
